Metadata-Version: 2.1
Name: dnn-cool-activations
Version: 0.1.2
Summary: dnn_cool_activations: Simple Numpy activation functions
Home-page: https://github.com/microlib-org/dnn_cool_activations
Author: Hristo Vrigazov
Author-email: hvrigazov@gmail.com
License: MIT
Platform: UNKNOWN
Classifier: License :: OSI Approved :: MIT License
Classifier: Programming Language :: Python :: 3
Classifier: Programming Language :: Python :: 3.4
Classifier: Programming Language :: Python :: 3.5
Classifier: Programming Language :: Python :: 3.6
Classifier: Programming Language :: Python :: 3.7
Classifier: Programming Language :: Python :: 3.8
Classifier: Programming Language :: Python :: 3.9
Classifier: Programming Language :: Python :: 3.10
Classifier: Programming Language :: Python :: 3.11
Classifier: Operating System :: OS Independent
License-File: LICENSE
